{"name": "Beaconsfield", "state": "WA", "postcode": "6162", "schools": [{"id": 48269, "slug": "winterfold-primary-school-6162", "name": "Winterfold Primary School", "type": "Primary", "sector": "Government", "icsea": 1057, "enrolments": 321}, {"id": 48868, "slug": "christ-the-king-school-6162", "name": "Christ the King School", "type": "Primary", "sector": "Catholic", "icsea": 1069, "enrolments": 304}, {"id": 50168, "slug": "beaconsfield-primary-school-6162", "name": "Beaconsfield Primary School", "type": "Primary", "sector": "Government", "icsea": 1090, "enrolments": 551}, {"id": 52276, "slug": "fremantle-college-6162", "name": "Fremantle College", "type": "Secondary", "sector": "Government", "icsea": 1004, "enrolments": 1312}]}