{"name": "Bell Post Hill", "state": "VIC", "postcode": "3215", "schools": [{"id": 44878, "slug": "rollins-primary-school-3215", "name": "Rollins Primary School", "type": "Primary", "sector": "Government", "icsea": 1001, "enrolments": 326}, {"id": 46257, "slug": "covenant-college-3215", "name": "Covenant College", "type": "Combined", "sector": "Independent", "icsea": 1070, "enrolments": 735}, {"id": 46332, "slug": "kardinia-international-college-3215", "name": "Kardinia International College", "type": "Combined", "sector": "Independent", "icsea": 1155, "enrolments": 1925}]}