{"name": "Berkeley", "state": "NSW", "postcode": "2506", "schools": [{"id": 42725, "slug": "berkeley-public-school-2506", "name": "Berkeley Public School", "type": "Primary", "sector": "Government", "icsea": 926, "enrolments": 259}, {"id": 42864, "slug": "berkeley-west-public-school-2506", "name": "Berkeley West Public School", "type": "Primary", "sector": "Government", "icsea": 868, "enrolments": 157}, {"id": 42913, "slug": "illawarra-sports-high-school-2506", "name": "Illawarra Sports High School", "type": "Secondary", "sector": "Government", "icsea": 937, "enrolments": 926}]}