{"name": "Birrong", "state": "NSW", "postcode": "2143", "schools": [{"id": 41449, "slug": "birrong-public-school-2143", "name": "Birrong Public School", "type": "Primary", "sector": "Government", "icsea": 967, "enrolments": 451}, {"id": 41564, "slug": "birrong-boys-high-school-2143", "name": "Birrong Boys High School", "type": "Secondary", "sector": "Government", "icsea": 937, "enrolments": 366}, {"id": 41614, "slug": "birrong-girls-high-school-2143", "name": "Birrong Girls High School", "type": "Secondary", "sector": "Government", "icsea": 956, "enrolments": 726}]}