{"name": "Braybrook", "state": "VIC", "postcode": "3019", "schools": [{"id": 40698, "slug": "western-english-language-school-3019", "name": "Western English Language School", "type": "Special", "sector": "Government", "icsea": 903, "enrolments": 502}, {"id": 40900, "slug": "caroline-chisholm-catholic-college-3019", "name": "Caroline Chisholm Catholic College", "type": "Secondary", "sector": "Catholic", "icsea": 1036, "enrolments": 1555}, {"id": 44844, "slug": "rosamond-school-3019", "name": "Rosamond School", "type": "Special", "sector": "Government", "icsea": 1012, "enrolments": 145}, {"id": 45238, "slug": "dinjerra-primary-school-3019", "name": "Dinjerra Primary School", "type": "Primary", "sector": "Government", "icsea": 1010, "enrolments": 217}, {"id": 45360, "slug": "braybrook-college-3019", "name": "Braybrook College", "type": "Secondary", "sector": "Government", "icsea": 977, "enrolments": 1373}, {"id": 45904, "slug": "christ-the-king-primary-school-3019", "name": "Christ the King Primary School", "type": "Primary", "sector": "Catholic", "icsea": 1006, "enrolments": 211}]}