{"name": "Craigieburn", "state": "VIC", "postcode": "3064", "schools": [{"id": 44836, "slug": "craigieburn-primary-school-3064", "name": "Craigieburn Primary School", "type": "Primary", "sector": "Government", "icsea": 979, "enrolments": 458}, {"id": 45108, "slug": "craigieburn-south-primary-school-3064", "name": "Craigieburn South Primary School", "type": "Primary", "sector": "Government", "icsea": 960, "enrolments": 545}, {"id": 45165, "slug": "willmott-park-primary-school-3064", "name": "Willmott Park Primary School", "type": "Primary", "sector": "Government", "icsea": 984, "enrolments": 626}, {"id": 45496, "slug": "craigieburn-secondary-college-3064", "name": "Craigieburn Secondary College", "type": "Secondary", "sector": "Government", "icsea": 918, "enrolments": 1008}, {"id": 45585, "slug": "mount-ridley-p-12-college-3064", "name": "Mount Ridley P-12 College", "type": "Combined", "sector": "Government", "icsea": 969, "enrolments": 2788}, {"id": 46050, "slug": "our-lady's-school-3064", "name": "Our Lady's School", "type": "Primary", "sector": "Catholic", "icsea": 984, "enrolments": 703}, {"id": 46124, "slug": "mother-teresa-school-3064", "name": "Mother Teresa School", "type": "Primary", "sector": "Catholic", "icsea": 1026, "enrolments": 342}, {"id": 50266, "slug": "aitken-creek-primary-school-3064", "name": "Aitken Creek Primary School", "type": "Primary", "sector": "Government", "icsea": 992, "enrolments": 972}, {"id": 52391, "slug": "oscar-romero-catholic-primary-school-3064", "name": "Oscar Romero Catholic Primary School", "type": "Primary", "sector": "Catholic", "icsea": 1010, "enrolments": 660}, {"id": 52479, "slug": "newbury-primary-school-3064", "name": "Newbury Primary School", "type": "Primary", "sector": "Government", "icsea": 1032, "enrolments": 1136}, {"id": 52696, "slug": "aitken-hill-primary-school-3064", "name": "Aitken Hill Primary School", "type": "Primary", "sector": "Government", "icsea": 1004, "enrolments": 892}, {"id": 52779, "slug": "elevation-secondary-college-3064", "name": "Elevation Secondary College", "type": "Secondary", "sector": "Government", "icsea": 962, "enrolments": 1177}, {"id": 53186, "slug": "wayi-school-3064", "name": "Wayi School", "type": "Special", "sector": "Government", "icsea": 994, "enrolments": 192}]}