{"name": "Mount Evelyn", "state": "VIC", "postcode": "3796", "schools": [{"id": 44631, "slug": "mount-evelyn-primary-school-3796", "name": "Mount Evelyn Primary School", "type": "Primary", "sector": "Government", "icsea": 1031, "enrolments": 397}, {"id": 44991, "slug": "birmingham-primary-school-3796", "name": "Birmingham Primary School", "type": "Primary", "sector": "Government", "icsea": 1040, "enrolments": 666}, {"id": 45111, "slug": "yarra-ranges-special-developmental-school-3796", "name": "Yarra Ranges Special Developmental School", "type": "Special", "sector": "Government", "icsea": 993, "enrolments": 89}, {"id": 46047, "slug": "st-mary's-school-3796", "name": "St Mary's School", "type": "Primary", "sector": "Catholic", "icsea": 1018, "enrolments": 324}, {"id": 46229, "slug": "mount-evelyn-christian-school-3796", "name": "Mount Evelyn Christian School", "type": "Combined", "sector": "Independent", "icsea": 1059, "enrolments": 693}]}