{"name": "New Town", "state": "TAS", "postcode": "7008", "schools": [{"id": 40112, "slug": "new-town-primary-school-7008", "name": "New Town Primary School", "type": "Primary", "sector": "Government", "icsea": 1057, "enrolments": 305}, {"id": 40238, "slug": "sacred-heart-college-7008", "name": "Sacred Heart College", "type": "Combined", "sector": "Catholic", "icsea": 1017, "enrolments": 934}, {"id": 53087, "slug": "hobart-city-high-school-7008", "name": "Hobart City High School", "type": "Secondary", "sector": "Government", "icsea": 987, "enrolments": 844}]}