{"name": "Quakers Hill", "state": "NSW", "postcode": "2763", "schools": [{"id": 40646, "slug": "wyndham-college-2763", "name": "Wyndham College", "type": "Secondary", "sector": "Government", "icsea": 1003, "enrolments": 378}, {"id": 41663, "slug": "quakers-hill-public-school-2763", "name": "Quakers Hill Public School", "type": "Primary", "sector": "Government", "icsea": 1097, "enrolments": 962}, {"id": 41774, "slug": "hambledon-public-school-2763", "name": "Hambledon Public School", "type": "Primary", "sector": "Government", "icsea": 1072, "enrolments": 633}, {"id": 41777, "slug": "barnier-public-school-2763", "name": "Barnier Public School", "type": "Primary", "sector": "Government", "icsea": 1078, "enrolments": 788}, {"id": 41846, "slug": "quakers-hill-high-school-2763", "name": "Quakers Hill High School", "type": "Secondary", "sector": "Government", "icsea": 1025, "enrolments": 925}, {"id": 43191, "slug": "mary-immaculate-primary-school-2763", "name": "Mary Immaculate Primary School", "type": "Primary", "sector": "Catholic", "icsea": 1098, "enrolments": 598}]}