{"name": "Riverside", "state": "TAS", "postcode": "7250", "schools": [{"id": 40014, "slug": "st-anthony's-catholic-school-7250", "name": "St Anthony's Catholic School", "type": "Primary", "sector": "Catholic", "icsea": 1026, "enrolments": 180}, {"id": 40031, "slug": "launceston-christian-school-7250", "name": "Launceston Christian School", "type": "Combined", "sector": "Independent", "icsea": 1070, "enrolments": 742}, {"id": 40081, "slug": "riverside-high-school-7250", "name": "Riverside High School", "type": "Secondary", "sector": "Government", "icsea": 1009, "enrolments": 624}, {"id": 40158, "slug": "riverside-primary-school-7250", "name": "Riverside Primary School", "type": "Primary", "sector": "Government", "icsea": 1018, "enrolments": 673}]}