{"name": "Stanmore", "state": "NSW", "postcode": "2048", "schools": [{"id": 41145, "slug": "stanmore-public-school-2048", "name": "Stanmore Public School", "type": "Primary", "sector": "Government", "icsea": 1138, "enrolments": 560}, {"id": 43459, "slug": "st-michael's-catholic-primary-school-2048", "name": "St Michael's Catholic Primary School", "type": "Primary", "sector": "Catholic", "icsea": 1160, "enrolments": 116}, {"id": 43877, "slug": "newington-college-2048", "name": "Newington College", "type": "Combined", "sector": "Independent", "icsea": 1182, "enrolments": 2072}]}