{"name": "Strathpine", "state": "QLD", "postcode": "4500", "schools": [{"id": 47079, "slug": "strathpine-state-school-4500", "name": "Strathpine State School", "type": "Primary", "sector": "Government", "icsea": 976, "enrolments": 372}, {"id": 47325, "slug": "strathpine-west-state-school-4500", "name": "Strathpine West State School", "type": "Primary", "sector": "Government", "icsea": 966, "enrolments": 419}, {"id": 47487, "slug": "pine-rivers-state-high-school-4500", "name": "Pine Rivers State High School", "type": "Secondary", "sector": "Government", "icsea": 960, "enrolments": 902}]}