{"name": "Thornbury", "state": "VIC", "postcode": "3071", "schools": [{"id": 44564, "slug": "wales-street-primary-school-3071", "name": "Wales Street Primary School", "type": "Primary", "sector": "Government", "icsea": 1140, "enrolments": 616}, {"id": 44656, "slug": "penders-grove-primary-school-3071", "name": "Penders Grove Primary School", "type": "Primary", "sector": "Government", "icsea": 1021, "enrolments": 160}, {"id": 44663, "slug": "thornbury-primary-school-3071", "name": "Thornbury Primary School", "type": "Primary", "sector": "Government", "icsea": 1093, "enrolments": 308}, {"id": 45322, "slug": "virtual-school-victoria-3071", "name": "Virtual School Victoria", "type": "Combined", "sector": "Government", "icsea": 1073, "enrolments": 6248}, {"id": 45533, "slug": "thornbury-high-school-3071", "name": "Thornbury High School", "type": "Secondary", "sector": "Government", "icsea": 1067, "enrolments": 1123}, {"id": 45791, "slug": "st-mary's-school-3071", "name": "St Mary's School", "type": "Primary", "sector": "Catholic", "icsea": 1089, "enrolments": 113}, {"id": 45885, "slug": "holy-spirit-school-3071", "name": "Holy Spirit School", "type": "Primary", "sector": "Catholic", "icsea": 1107, "enrolments": 129}]}